git_garden/__init__.py
git_garden/__main__.py
git_garden/cli.py
git_garden-1.1.7.dist-info/METADATA
git_garden-1.1.7.dist-info/WHEEL
git_garden-1.1.7.dist-info/entry_points.txt
git_garden-1.1.7.dist-info/RECORD
