Metadata-Version: 2.4
Name: git-garden
Version: 1.1.7
Summary: A simple Python git wrapper to help manage multi-project maintenance.
Project-URL: Homepage, https://github.com/c0ff33-dev/git-garden
Project-URL: Documentation, https://git-garden.readthedocs.io/latest/
Project-URL: Repository, https://github.com/c0ff33-dev/git-garden.git
Author: c0ff33-dev
Keywords: git
Classifier: Development Status :: 5 - Production/Stable
Classifier: Intended Audience :: Developers
Classifier: Programming Language :: Python :: 3.10
Classifier: Programming Language :: Python :: 3.11
Classifier: Programming Language :: Python :: 3.12
Classifier: Programming Language :: Python :: 3.13
Requires-Python: >=3.10
Requires-Dist: click
Provides-Extra: dev
Requires-Dist: mypy; extra == 'dev'
Requires-Dist: pydoclint; extra == 'dev'
Requires-Dist: pytest; extra == 'dev'
Requires-Dist: pytest-cov; extra == 'dev'
Requires-Dist: ruff; extra == 'dev'
Requires-Dist: sphinx; extra == 'dev'
Requires-Dist: sphinx-autodoc-typehints; extra == 'dev'
Requires-Dist: tox; extra == 'dev'
